general_sam-1.0.3.dist-info/METADATA
general_sam-1.0.3.dist-info/WHEEL
general_sam-1.0.3.dist-info/licenses/LICENSE-APACHE
general_sam-1.0.3.dist-info/licenses/LICENSE-MIT
general_sam/__init__.py
general_sam/general_sam.abi3.so
general_sam/general_sam.pyi
general_sam/trie_utils.py
general_sam/vocab_prefix.py
general_sam-1.0.3.dist-info/RECORD
